CONTRIBUTING.md
LICENSE
MANIFEST.in
README.md
VERSION
setup.cfg
setup.py
docs/Makefile
docs/conf.py
docs/index.rst
docs/make.bat
src/dowel/__init__.py
src/dowel/csv_output.py
src/dowel/histogram.py
src/dowel/logger.py
src/dowel/simple_outputs.py
src/dowel/tabular_input.py
src/dowel/tensor_board_output.py
src/dowel/utils.py
src/dowel.egg-info/PKG-INFO
src/dowel.egg-info/SOURCES.txt
src/dowel.egg-info/dependency_links.txt
src/dowel.egg-info/requires.txt
src/dowel.egg-info/top_level.txt
tests/__init__.py
tests/fixtures.py
tests/dowel/__init__.py
tests/dowel/test_csv_output.py
tests/dowel/test_logger.py
tests/dowel/test_simple_outputs.py
tests/dowel/test_tabular_input.py
tests/dowel/test_tensor_board_output.py